isoadverse/__init__.py
isoadverse/setup.py
isoadverse/attacks/__init__.py
isoadverse/attacks/deepwordbug.py
isoadverse/attacks/text_fgsm.py
isoadverse/attacks/text_pgd.py
isoadverse/attacks/textbugger.py
isoadverse/tests/__init__.py
isoadverse/tests/test_text_fgsm.py
isoadverse/tests/test_text_pgd.py
isoadverse/utils/__init__.py
isoadverse/utils/data_loader.py
isoadverse/utils/model_loader.py
iso_adverse-0.2.0.dist-info/LICENSE
iso_adverse-0.2.0.dist-info/METADATA
iso_adverse-0.2.0.dist-info/WHEEL
iso_adverse-0.2.0.dist-info/top_level.txt
iso_adverse-0.2.0.dist-info/RECORD
