Metadata-Version: 2.1
Name: iso-adverse
Version: 0.2.0
Summary: This package is designed to simulate adversarial on pre-trained language models (pre-LLM models)
Home-page: https://github.com/iso-ai/isoadverse
Author: Jazmia Henry
Author-email: isojaz@isoai.co
License: Apache License 2.0
Platform: UNKNOWN
Classifier: Programming Language :: Python :: 3
Classifier: License :: OSI Approved :: Apache Software License
Classifier: Operating System :: OS Independent
Requires-Python: >=3.6
License-File: LICENSE
Requires-Dist: torch (>=1.7.0)
Requires-Dist: transformers (>=4.0.0)
